NepTrainKit/config.py
NepTrainKit/main.py
NepTrainKit/nep_cpu.cp311-win_amd64.pyd
NepTrainKit/nep_gpu.cp311-win_amd64.exp
NepTrainKit/nep_gpu.cp311-win_amd64.lib
NepTrainKit/nep_gpu.cp311-win_amd64.pyd
NepTrainKit/paths.py
NepTrainKit/src_rc.py
NepTrainKit/utils.py
NepTrainKit/version.py
NepTrainKit/_version.py
NepTrainKit/__init__.py
NepTrainKit/Config/config.sqlite
NepTrainKit/Config/nep.json
NepTrainKit/Config/nep89.txt
NepTrainKit/Config/ptable.json
NepTrainKit/core/calculator.py
NepTrainKit/core/card_manager.py
NepTrainKit/core/cstdio_redirect.py
NepTrainKit/core/energy_shift.py
NepTrainKit/core/message.py
NepTrainKit/core/structure.py
NepTrainKit/core/torsion_guard_pbc.py
NepTrainKit/core/types.py
NepTrainKit/core/utils.py
NepTrainKit/core/_fastxyz.cp311-win_amd64.pyd
NepTrainKit/core/__init__.py
NepTrainKit/core/dataset/database.py
NepTrainKit/core/dataset/manager.py
NepTrainKit/core/dataset/models.py
NepTrainKit/core/dataset/services.py
NepTrainKit/core/dataset/__init__.py
NepTrainKit/core/io/base.py
NepTrainKit/core/io/deepmd.py
NepTrainKit/core/io/importers.py
NepTrainKit/core/io/nep.py
NepTrainKit/core/io/registry.py
NepTrainKit/core/io/sampler.py
NepTrainKit/core/io/__init__.py
NepTrainKit/ui/dialogs.py
NepTrainKit/ui/messages.py
NepTrainKit/ui/threads.py
NepTrainKit/ui/update.py
NepTrainKit/ui/updater.py
NepTrainKit/ui/__init__.py
NepTrainKit/ui/canvas/__init__.py
NepTrainKit/ui/canvas/base/canvas.py
NepTrainKit/ui/canvas/base/__init__.py
NepTrainKit/ui/canvas/pyqtgraph/canvas.py
NepTrainKit/ui/canvas/pyqtgraph/structure.py
NepTrainKit/ui/canvas/pyqtgraph/__init__.py
NepTrainKit/ui/canvas/vispy/canvas.py
NepTrainKit/ui/canvas/vispy/structure.py
NepTrainKit/ui/canvas/vispy/__init__.py
NepTrainKit/ui/pages/data_manager.py
NepTrainKit/ui/pages/makedata.py
NepTrainKit/ui/pages/settings.py
NepTrainKit/ui/pages/show_nep.py
NepTrainKit/ui/pages/__init__.py
NepTrainKit/ui/views/cards.py
NepTrainKit/ui/views/dataset_widget.py
NepTrainKit/ui/views/nep.py
neptrainkit-2.8.1.dist-info/DELVEWHEEL
neptrainkit-2.8.1.dist-info/entry_points.txt
neptrainkit-2.8.1.dist-info/METADATA
neptrainkit-2.8.1.dist-info/RECORD
neptrainkit-2.8.1.dist-info/top_level.txt
neptrainkit-2.8.1.dist-info/WHEEL
neptrainkit-2.8.1.dist-info/licenses/LICENSE
