Metadata-Version: 2.4
Name: NepTrainKit
Version: 2.8.1
Summary: NepTrainKit is a Python package for visualizing and manipulating training datasets for NEP.
Author: Chen Cheng bing
Author-email: Chen Cheng bing <1747193328@qq.com>
License: GPL-3.0
Project-URL: Homepage, https://github.com/aboys-cb/NepTrainKit
Project-URL: Documentation, https://github.com/aboys-cb/NepTrainKit
Project-URL: Repository, https://github.com/aboys-cb/NepTrainKit
Project-URL: Issues, https://github.com/aboys-cb/NepTrainKit/issues
Classifier: Development Status :: 4 - Beta
Classifier: Intended Audience :: Science/Research
Classifier: Operating System :: OS Independent
Classifier: Programming Language :: Python :: 3
Classifier: Programming Language :: Python :: 3.10
Classifier: Programming Language :: Python :: 3.11
Classifier: Programming Language :: Python :: 3.12
Classifier: License :: OSI Approved :: GNU General Public License v3 or later (GPLv3+)
Classifier: Topic :: Scientific/Engineering :: Chemistry
Classifier: Topic :: Scientific/Engineering :: Information Analysis
Classifier: Topic :: Scientific/Engineering :: Physics
Classifier: Topic :: Software Development :: Libraries :: Python Modules
Requires-Python: >=3.10
License-File: LICENSE
Requires-Dist: PySide6==6.9.0
Requires-Dist: PySide6-Fluent-Widgets>=1.7.0
Requires-Dist: loguru>=0.7.2
Requires-Dist: requests>=2.32.3
Requires-Dist: pyqtgraph>=0.13.7
Requires-Dist: PyOpenGL>=3.1.7
Requires-Dist: numpy>=1.26.0
Requires-Dist: vispy>=0.14.3
Requires-Dist: ase
Requires-Dist: scipy>=1.15.0
Requires-Dist: pybind11
Requires-Dist: SQLAlchemy>=2.0.0
Provides-Extra: test
Requires-Dist: pytest>=7.0; extra == "test"
Requires-Dist: pytest-qt>=4.2.0; extra == "test"
Requires-Dist: pytest-cov>=4.0.0; extra == "test"
Requires-Dist: codecov>=2.0.0; extra == "test"
Dynamic: author
Dynamic: license-file
